{
  "snapshots": [
    {
      "id": 5,
      "name": "groovydev-2022-07-20T18:35:39.626Z",
      "description": null,
      "externalId": "snapshot-93001",
      "status": "complete",
      "state": null,
      "snapshotType": "vm",
      "snapshotCreated": "2022-07-20T18:35:58Z",
      "zone": {
        "id": 15,
        "name": "vcenter1 - homelab"
      },
      "datastore": null,
      "parentSnapshot": null,
      "currentlyActive": true,
      "memorySnapshot": false,
      "dateCreated": "2022-07-20T18:35:42Z"
    }
  ]
}