{
    "integration": {
        "id": 6254,
        "name": "Labs vRO",
        "enabled": true,
        "type": "vro",
        "integrationType": {
            "id": 31,
            "code": "vro",
            "name": "vRealize Orchestrator"
        },
        "url": "https://vra7.fqdn.com",
        "token": "************",
        "tokenHash": "a9c1352e1c60622284c7d6606d45a6453d85",
        "authType": "oauth",
        "authId": "cafe_cli-KjR8PA",
        "isPlugin": false,
        "config": {},
        "status": "ok",
        "statusDate": "2022-09-01T17:34:48Z",
        "statusMessage": null,
        "lastSync": null,
        "lastSyncDuration": null,
        "credential": {
            "id": 1019,
            "name": "Integration: vRO",
            "type": "username-password",
            "types": [
                "username-password"
            ]
        }
    }
}